dkbotzz/__init__.py
dkbotzz/forcesub.py
dkbotzz/func.py
dkbotzz/function.py
dkbotzz/imdb.py
dkbotzz/translation.py
dkbotzz-0.4.9.dist-info/LICENSE
dkbotzz-0.4.9.dist-info/METADATA
dkbotzz-0.4.9.dist-info/WHEEL
dkbotzz-0.4.9.dist-info/top_level.txt
dkbotzz-0.4.9.dist-info/RECORD
