Metadata-Version: 2.1
Name: dkbotzz
Version: 0.4.9
Summary: Package containing basic functions to build telegram bots.
Home-page: https://github.com/DKBOTZNETWORK
Author: DK BOTZ
License: GNU AFFERO GENERAL PUBLIC LICENSE (v3)
Classifier: Programming Language :: Python :: 3
Classifier: Programming Language :: Python :: 3.6
Classifier: Programming Language :: Python :: 3.7
Classifier: Programming Language :: Python :: 3.8
Classifier: Programming Language :: Python :: 3.9
Classifier: License :: OSI Approved :: GNU General Public License v3 (GPLv3)
Classifier: Operating System :: OS Independent
Requires-Python: >=3.6
License-File: LICENSE
Requires-Dist: pyrogram
Requires-Dist: requests
Requires-Dist: gTTS
Requires-Dist: mdiskpro
Requires-Dist: googletrans (==3.1.0a0)
